{
  "outcomes": {
    "label": "Global impact made tangible for fast moving product teams",
    "title": {
      "pre": "What I've delivered.",
      "em": "",
      "post": ""
    },
    "heroNum": "13M + users",
    "heroLead": "Delivering clinical impact across multiple contexts globally",
    "heroBody": "Led product delivery teams integrating regulatory certified clinical AI into health systems in US, Europe and Africa",
    "items": [
      {
        "title": "Making clinical outcomes tangible for product teams",
        "body": "Established and implemented a clinical outcomes, risk and quality framework that levelled up the product development life cycle at one of Europe's largest health tech companies. "
      },
      {
        "title": "Clinical leadership that supports business outcomes",
        "body": "Fast embedding helped a UK startup restructure its evidence generation strategy, resulting in a successful funding round, regulatory certification and NHS procurement success. "
      }
    ]
  },
  "layout": [
    {
      "id": "gap",
      "theme": "light"
    },
    {
      "id": "stats",
      "theme": "pink"
    },
    {
      "id": "practice",
      "theme": "dark"
    },
    {
      "id": "testimonials",
      "theme": "light"
    },
    {
      "id": "work",
      "theme": "light"
    },
    {
      "id": "outcomes",
      "theme": "dark"
    },
    {
      "id": "who",
      "theme": "light"
    },
    {
      "id": "inlinecta",
      "theme": "dark"
    },
    {
      "id": "quote",
      "theme": "dark"
    },
    {
      "id": "contact",
      "theme": "dark"
    }
  ],
  "cta": {
    "label": "Let's work together",
    "title": {
      "pre": "Ready to build something ",
      "em": "the right way?",
      "post": ""
    },
    "body": "Whether you're building digital health that has to work in the real world, or backing the people who do, every conversation starts with what you're actually trying to build.",
    "ctaLabel": "Get in touch →",
    "ctaHref": "/contact"
  },
  "thinkingHead": {
    "moreHref": "/thinking",
    "podBody": "Candid conversations with the people reshaping digital health across 60+ countries.",
    "podLinkHref": "https://gpodh.org",
    "podTitle": "Global Perspectives on Digital Health",
    "podImageAlt": "Shubs, host",
    "label": "From Shubs",
    "podLinkLabel": "Listen on gpodh.org →",
    "podImage": "/images/shubs-pink.webp",
    "podKicker": "Hosted by Dr Shubs Upadhyay · The GPODH Podcast",
    "title": {
      "pre": "Notes from the field.",
      "em": "",
      "post": ""
    },
    "moreLabel": "Read all insights →"
  },
  "work": {
    "label": "Case studies",
    "title": {
      "pre": "My work.",
      "em": "",
      "post": ""
    },
    "cards": [
      {
        "num": "01",
        "body": "Built and implemented medical quality and outcomes frameworks for Series B + companies that retained shipping velocity and generated evidence of effectiveness"
      },
      {
        "num": "02",
        "body": "Delivered keynotes to Tech and Product executive leadership to drive strategy and direction"
      },
      {
        "num": "03",
        "body": "Unified commercial narrative and impact evidence generation for a scaling clinical AI company"
      }
    ]
  },
  "engagements": {
    "label": "How I work · Three formats",
    "title": {
      "pre": "Three ways to level up your impact.",
      "em": "",
      "post": ""
    },
    "cards": [
      {
        "num": "01",
        "title": "Retainer Advisory",
        "body": "Ongoing senior counsel to founders and leadership teams. On-site presence where it matters, in the real decisions: board conversations, clinical-product reviews, evidence strategy, commercial alignment."
      },
      {
        "num": "02",
        "title": "Three-Month Sprint",
        "body": "A focused intensive designed to resolve a specific strategic or operational challenge. Defined scope, clear deliverables, and a concrete output your team can run with."
      },
      {
        "num": "03",
        "title": "Workshop & Keynote",
        "body": "A single high-impact session for leadership teams, boards, or investor portfolios. I run workshops and keynotes at companies and conferences across Europe."
      }
    ]
  },
  "testimonialsHead": {
    "label": "Testimonials",
    "title": {
      "pre": "What it's like to work with me.",
      "em": "",
      "post": ""
    }
  },
  "gap": {
    "label": "Why this matters",
    "title": {
      "pre": "I've lived the challenges.",
      "em": "",
      "post": ""
    },
    "rows": [
      {
        "n": "01",
        "tag": "The Problem",
        "heading": "What it costs when clinical comes in too late.",
        "paras": [
          {
            "lead": "",
            "text": "The digital health industry celebrates the wrong signals. Accuracy scores, engagement metrics, adoption curves. Easy to report, and none of it the same as health outcomes."
          },
          {
            "lead": "",
            "text": "Most products are built by smart, motivated people. The problem isn't technology or intent, it's that the definition of value gets decided too late, in the wrong room, by people who aren't equipped to make it. Clinical input arrives at the end to sign off rather than at the start to shape decisions."
          }
        ]
      },
      {
        "n": "02",
        "tag": "The Cost",
        "heading": "What it costs when this goes wrong.",
        "paras": [
          {
            "lead": "Builders and teams.",
            "text": "Deals stall in procurement because the clinical story wasn't built into the product from the start. Safety and quality incidents surface late and expensively. Regulatory submissions take three times as long as they should."
          },
          {
            "lead": "Funders and investors.",
            "text": "Portfolio companies report impressive activity metrics while missing the clinical outcomes that determine whether a health system buys, renews, or recommends. The gap between what was pitched and what actually works tends to stay hidden, until a renewal, audit or safety review brings it into the open."
          }
        ]
      },
      {
        "n": "03",
        "tag": "The Solution",
        "heading": "There's a better way to work, and I can help you build it.",
        "paras": [
          {
            "lead": "",
            "text": "Clinical rigour and product velocity are not opposites. They are a function of how clinical, product, commercial, and regulatory work is set up to happen together. When I come in early, shaping product decisions rather than reviewing them at the end, teams ship faster, build stronger evidence, and arrive at conversations with commissioners, regulators, and investors with a case that stands up."
          },
          {
            "lead": "",
            "text": "I work with founders, product leaders, and medical leaders to build that way of working, tuned to where your organisation actually is, not lifted from a framework."
          }
        ]
      }
    ]
  },
  "lived": {
    "label": "Why work with me",
    "title": {
      "pre": "Lived, ",
      "em": "not lifted.",
      "post": ""
    },
    "paras": [
      "I'm a physician who has spent a decade at the point where these problems actually get solved. As senior clinical and medical director at a venture-backed digital health company deploying regulated AI across multiple markets, my work was defining what good looked like, for which patients, against what counterfactual, and then building the practices that could deliver it at the pace the business demanded.",
      "That work has continued since. Co-chairing a WHO working group on AI evaluation. Clinical practice across different health systems. Keynotes for senior tech and product audiences at companies like Doctolib, the Wellcome Trust, and conferences across Europe.",
      "I don't bring an old playbook. I apply hard-won lessons from having lived your challenges, and fluently direct the conversation and translate that into dynamic actions that can support every discipline in the room."
    ],
    "tag": "Physician · Advisor · Host",
    "image": "/images/shubs-keynote.jpg",
    "imageAlt": "Dr Shubs Upadhyay delivering a keynote"
  },
  "hero": {
    "ctaPrimaryLabel": "Let's talk →",
    "imageAlt": "Dr Shubs Upadhyay",
    "ctaSecondaryHref": "/services",
    "ctaSecondaryLabel": "How I work →",
    "label": "Dr Shubs Upadhyay, Trusted Digital Health Advisor",
    "title": {
      "pre": "",
      "em": "Clinical rigour",
      "post": " at product speed."
    },
    "image": "/images/Shubs.webp",
    "lead": "A decade inside venture backed digital health as a senior clinician leader leading teams that delivered AI across clinical settings globally.\nI help companies and leaders build towards what matters in healthcare and help funders create the right conditions for this. ",
    "ctaPrimaryHref": "/contact"
  },
  "practice": {
    "label": "What I do",
    "title": {
      "pre": "Where I focus.",
      "em": "",
      "post": ""
    },
    "blocks": [
      {
        "num": "01",
        "title": "Clinical and Product Integration",
        "body": "Level up how clinical, product, QARA, data science, and engineering teams make decisions together. The pre-deployment work on product quality and robust monitoring lets you ship at pace and catch the right things proactively, without becoming a bottleneck or safety becoming an afterthought.",
        "list": [
          "Sharp, fast focus towards clinical outcomes for product teams",
          "Proactive quality monitoring after deployment",
          "Workshops on medical value and risk for tech and product leadership"
        ],
        "moreLabel": "Learn more →",
        "moreHref": "/services"
      },
      {
        "num": "02",
        "title": "Commercial and Clinical Alignment",
        "body": "As digital health companies scale, the sales narrative, the product roadmap, and the evidence strategy tend to drift apart. I bring them back into a single line, so what you're selling, what you're building, and what you're proving are the same story. Not a rebranding exercise, but product, commercial and evidence genuinely pulling the same way.",
        "list": [
          "Sales narrative aligned with clinical evidence",
          "Product, commercial, and evidence strategy as a single line",
          "Keynotes, executive engagement and offsites that drive strategy and direction"
        ],
        "moreLabel": "Learn more →",
        "moreHref": "/services"
      }
    ]
  },
  "quote": {
    "label": "What it boils down to",
    "pre": "Build the right thing.",
    "em": "Build the thing right",
    "cite": "Dr Shubs Upadhyay"
  },
  "who": {
    "label": "Who I work with",
    "title": {
      "pre": "I work with people who focus on what matters in healthcare",
      "em": "",
      "post": ""
    },
    "cards": [
      {
        "kicker": "People building",
        "title": "Digital health founders and their teams",
        "body": "When the clinical, product, commercial, and evidence challenges start to compound on each other, this is the engagement. I come in early, stay close, and build the ways of working that mean the next stage actually works.",
        "moreLabel": "See how I can help →",
        "moreHref": "/services"
      },
      {
        "kicker": "People leading",
        "title": "Clinical and medical leaders",
        "body": "Whether you are a CMO setting clinical strategy or a medical lead carrying the weight of safety and evidence, I am a sounding board and a partner, helping you make the case to your board, put the right practices in place, and stand firm on the things that actually affect patients.",
        "moreLabel": "See how I can help →",
        "moreHref": "/services"
      },
      {
        "kicker": "People investing",
        "title": "Philanthropy, foundations, and impact investors",
        "body": "I bring senior clinical-strategic perspective into diligence, portfolio support, and cohort programming, helping the organisations you back build toward outcomes they can stand behind.",
        "moreLabel": "See how I help investors →",
        "moreHref": "/services"
      }
    ]
  }
}
